wc_sandbox/VERSION
wc_sandbox/__init__.py
wc_sandbox/__main__.py
wc_sandbox-0.0.1.dist-info/METADATA
wc_sandbox-0.0.1.dist-info/RECORD
wc_sandbox-0.0.1.dist-info/WHEEL
wc_sandbox-0.0.1.dist-info/dependency_links.txt
wc_sandbox-0.0.1.dist-info/entry_points.txt
wc_sandbox-0.0.1.dist-info/top_level.txt
