Metadata-Version: 2.1
Name: wc-sandbox
Version: 0.0.1
Summary: Jupyter playground for whole-cell modeling
Home-page: https://github.com/KarrLab/wc_sandbox
Author: Karr Lab
Author-email: karr@mssm.com
License: MIT
Download-URL: https://github.com/KarrLab/wc_sandbox
Keywords: whole-cell modeling,computational biology,systems biology,modeling,simulation,jupyter
Platform: UNKNOWN
Classifier: Development Status :: 3 - Alpha
Classifier: License :: OSI Approved :: MIT License
Classifier: Programming Language :: Python
Classifier: Programming Language :: Python :: 3
Classifier: Natural Language :: English
Classifier: Operating System :: OS Independent
Classifier: Topic :: Scientific/Engineering :: Bio-Informatics
Provides-Extra: all
Provides-Extra: docs
Provides-Extra: tests
Requires-Dist: bpforms
Requires-Dist: cement
Requires-Dist: jupyter
Requires-Dist: jupyter-contrib-nbextensions
Requires-Dist: setuptools
Requires-Dist: wc-rules
Provides-Extra: all
Requires-Dist: capturer; extra == 'all'
Requires-Dist: mock; extra == 'all'
Requires-Dist: sphinx (>=1.8); extra == 'all'
Requires-Dist: sphinx-rtd-theme; extra == 'all'
Requires-Dist: sphinxcontrib-addmetahtml (>=0.1.1); extra == 'all'
Requires-Dist: sphinxcontrib-bibtex; extra == 'all'
Requires-Dist: sphinxcontrib-googleanalytics (>=0.1.1); extra == 'all'
Requires-Dist: sphinxcontrib-spelling; extra == 'all'
Provides-Extra: docs
Requires-Dist: sphinx (>=1.8); extra == 'docs'
Requires-Dist: sphinx-rtd-theme; extra == 'docs'
Requires-Dist: sphinxcontrib-addmetahtml (>=0.1.1); extra == 'docs'
Requires-Dist: sphinxcontrib-bibtex; extra == 'docs'
Requires-Dist: sphinxcontrib-googleanalytics (>=0.1.1); extra == 'docs'
Requires-Dist: sphinxcontrib-spelling; extra == 'docs'
Provides-Extra: tests
Requires-Dist: capturer; extra == 'tests'
Requires-Dist: mock; extra == 'tests'
